fapy/__init__.py
fapy/apis.py
fapy/checkers.py
fapy/net.py
fapy/stalk.py
fapy/utils.py
fapy-0.1.8.dist-info/METADATA
fapy-0.1.8.dist-info/WHEEL
fapy-0.1.8.dist-info/top_level.txt
fapy-0.1.8.dist-info/RECORD
