Metadata-Version: 2.1
Name: fapy
Version: 0.1.8
Summary: fagci's python library
Home-page: https://github.com/fagci/fapy/
Author: fagci
Author-email: fagci.nsk@gmail.com
License: UNKNOWN
Platform: UNKNOWN
